pysvg2pdf-0.1.0.dist-info/METADATA
pysvg2pdf-0.1.0.dist-info/WHEEL
pysvg2pdf-0.1.0.dist-info/license_files/LICENSE-APACHE
pysvg2pdf-0.1.0.dist-info/license_files/LICENSE-MIT
pysvg2pdf/__init__.py
pysvg2pdf/ffi.py
pysvg2pdf/pysvg2pdf.so
pysvg2pdf-0.1.0.dist-info/RECORD
