Metadata-Version: 2.3
Name: pysvg2pdf
Version: 0.1.0
Classifier: Programming Language :: Rust
Classifier: Programming Language :: Python :: Implementation :: CPython
Classifier: Programming Language :: Python :: Implementation :: PyPy
Requires-Dist: cffi
License-File: LICENSE-APACHE
License-File: LICENSE-MIT
Requires-Python: >=3.8
